Metadata-Version: 1.1
Name: ensembles
Version: 0.1.5
Summary: A package for ensembling of machine learning models
Home-page: https://github.com/unnati-xyz/ensemble-package
Author: Prajwal Kailas
Author-email: prajwal967@gmail.com
License: MIT
Keywords: Ensemble
Platform: UNKNOWN
Classifier: Development Status :: 3 - Alpha
Classifier: License :: OSI Approved :: MIT License
Classifier: Programming Language :: Python :: 2
Classifier: Programming Language :: Python :: 2.6
Classifier: Programming Language :: Python :: 2.7
Classifier: Programming Language :: Python :: 3
Classifier: Programming Language :: Python :: 3.2
Classifier: Programming Language :: Python :: 3.3
Classifier: Programming Language :: Python :: 3.4
